prettytensor/__init__.py
prettytensor/bookkeeper.py
prettytensor/bookkeeper_test.py
prettytensor/chain_dict.py
prettytensor/chain_dict_test.py
prettytensor/funcs.py
prettytensor/functions.py
prettytensor/functions_test.py
prettytensor/input_helpers.py
prettytensor/layers.py
prettytensor/local_trainer.py
prettytensor/local_trainer_test.py
prettytensor/parameters.py
prettytensor/pretty_tensor_class.py
prettytensor/pretty_tensor_image_methods.py
prettytensor/pretty_tensor_loss_methods.py
prettytensor/pretty_tensor_methods.py
prettytensor/pretty_tensor_normalization_methods.py
prettytensor/pretty_tensor_sparse_methods.py
prettytensor/pretty_tensor_test.py
prettytensor/pretty_tensor_testing.py
prettytensor/recurrent_networks.py
prettytensor/recurrent_networks_test.py
prettytensor/recurrent_networks_testing_utils.py
prettytensor/replay_queue.py
prettytensor/replay_queue_test.py
prettytensor/scopes.py
prettytensor/scopes_test.py
prettytensor/sequence_with_deltas.py
prettytensor/templated_pretty_tensor_test.py
prettytensor/train.py
prettytensor/tutorial/__init__.py
prettytensor/tutorial/baby_names.csv
prettytensor/tutorial/baby_names.py
prettytensor/tutorial/data_utils.py
prettytensor/tutorial/mnist.py
prettytensor/tutorial/shakespeare.py
prettytensor-0.7.4.dist-info/DESCRIPTION.rst
prettytensor-0.7.4.dist-info/METADATA
prettytensor-0.7.4.dist-info/RECORD
prettytensor-0.7.4.dist-info/WHEEL
prettytensor-0.7.4.dist-info/entry_points.txt
prettytensor-0.7.4.dist-info/metadata.json
prettytensor-0.7.4.dist-info/top_level.txt
